MANIFEST.in
README.md
setup.py
ptcache/__init__.py
ptcache/base.py
ptcache/cache.py
ptcache.egg-info/PKG-INFO
ptcache.egg-info/SOURCES.txt
ptcache.egg-info/dependency_links.txt
ptcache.egg-info/not-zip-safe
ptcache.egg-info/requires.txt
ptcache.egg-info/top_level.txt