Metadata-Version: 1.0
Name: ptcache
Version: 1.0.0
Summary: Simple and extensible cache for python.
Home-page: UNKNOWN
Author: Beginman
Author-email: xinxinyu2011@163.com
License: BSD
Platform: any
